vcrs/__init__.py
vcrs/vcr_cassette.py
vcrs/vcr_timer.py
casprotpy-1.0.1.dist-info/METADATA
casprotpy-1.0.1.dist-info/WHEEL
casprotpy-1.0.1.dist-info/top_level.txt
casprotpy-1.0.1.dist-info/RECORD
