Metadata-Version: 2.1
Name: casprotpy
Version: 1.0.1
Summary: Python project for generate CAS Protocol TGTs and STs
Home-page: UNKNOWN
Author: Fred William
Author-email: fred.william.prates@gmail.com
License: UNKNOWN
Platform: UNKNOWN
Classifier: Programming Language :: Python :: 3.6
Classifier: Development Status :: 5 - Production/Stable
Classifier: Topic :: Software Development :: Libraries :: Python Modules
Classifier: License :: OSI Approved :: MIT License
Classifier: Operating System :: OS Independent
Requires-Python: >=3.6
